hawktuner/__init__.py
hawktuner/tuner.py
hawktuner-0.0.10.dist-info/METADATA
hawktuner-0.0.10.dist-info/WHEEL
hawktuner-0.0.10.dist-info/top_level.txt
hawktuner-0.0.10.dist-info/RECORD
