Metadata-Version: 2.1
Name: hawktuner
Version: 0.0.10
Summary: ML DL tuner
Home-page: https://github.com/Torng/hawktuner
Author: hawktorng
Author-email: cool870427@gmail.com
License: UNKNOWN
Platform: UNKNOWN
Classifier: Programming Language :: Python :: 3
Classifier: License :: OSI Approved :: MIT License
Classifier: Operating System :: OS Independent
Requires-Python: >=3.6
